copclib/__init__.py
copclib/_core.cpython-313-x86_64-linux-gnu.so
copclib/_core.pyi
copclib/include/lazperf/filestream.hpp
copclib/include/lazperf/header.hpp
copclib/include/lazperf/lazperf.hpp
copclib/include/lazperf/lazperf_base.hpp
copclib/include/lazperf/readers.hpp
copclib/include/lazperf/vlr.hpp
copclib/include/lazperf/writers.hpp
copclib/lib/liblazperf.so
copclib/lib/cmake/LAZPERF/lazperf-config-version.cmake
copclib/lib/cmake/LAZPERF/lazperf-config.cmake
copclib/lib/cmake/LAZPERF/lazperf-targets-release.cmake
copclib/lib/cmake/LAZPERF/lazperf-targets.cmake
copclib/mp/__init__.py
copclib/mp/read.py
copclib/mp/transform.py
copclib/mp/utils.py
copclib-2.6.3.dist-info/METADATA
copclib-2.6.3.dist-info/WHEEL
copclib-2.6.3.dist-info/top_level.txt
copclib-2.6.3.dist-info/RECORD
copclib-2.6.3.dist-info/licenses/LICENSE.md
