Metadata-Version: 2.1
Name: copclib
Version: 2.6.3
Summary: copc-lib provides an easy-to-use interface for reading and creating Cloud Optimized Point Clouds
Home-page: https://github.com/RockRobotic/copc-lib
Author: Rock Robotic Inc.
Author-email: support@rockrobotic.com
Maintainer: Rock Robotic Inc.
Maintainer-email: support@rockrobotic.com
License: BSD
Keywords: point cloud spatial copc
Classifier: Development Status :: 5 - Production/Stable
Classifier: Intended Audience :: Developers
Classifier: Intended Audience :: Science/Research
Classifier: License :: OSI Approved :: BSD License
Classifier: Operating System :: OS Independent
Classifier: Programming Language :: Python :: 3.7
Classifier: Programming Language :: Python :: 3.8
Classifier: Programming Language :: Python :: 3.9
Classifier: Programming Language :: Python :: 3.10
Classifier: Topic :: Scientific/Engineering :: GIS
License-File: LICENSE.md
Provides-Extra: test
Requires-Dist: pytest ; extra == 'test'
Requires-Dist: numpy ; extra == 'test'
